{"nodes": [{"id": "d_prism_apps_widget_src_cursor_ts", "label": "cursor.ts", "file_type": "code", "source_file": "D:\\prism\\apps\\widget\\src\\cursor.ts", "source_location": "L1"}, {"id": "cursor_getcursor", "label": "getCursor()", "file_type": "code", "source_file": "D:\\prism\\apps\\widget\\src\\cursor.ts", "source_location": "L17"}, {"id": "cursor_createcursor", "label": "createCursor()", "file_type": "code", "source_file": "D:\\prism\\apps\\widget\\src\\cursor.ts", "source_location": "L21"}, {"id": "cursor_removecursor", "label": "removeCursor()", "file_type": "code", "source_file": "D:\\prism\\apps\\widget\\src\\cursor.ts", "source_location": "L41"}, {"id": "cursor_movecursortoelement", "label": "moveCursorToElement()", "file_type": "code", "source_file": "D:\\prism\\apps\\widget\\src\\cursor.ts", "source_location": "L46"}, {"id": "cursor_pulsefield", "label": "pulseField()", "file_type": "code", "source_file": "D:\\prism\\apps\\widget\\src\\cursor.ts", "source_location": "L61"}, {"id": "cursor_typeintofield", "label": "typeIntoField()", "file_type": "code", "source_file": "D:\\prism\\apps\\widget\\src\\cursor.ts", "source_location": "L73"}, {"id": "cursor_animatedfillfields", "label": "animatedFillFields()", "file_type": "code", "source_file": "D:\\prism\\apps\\widget\\src\\cursor.ts", "source_location": "L120"}], "edges": [{"source": "d_prism_apps_widget_src_cursor_ts", "target": "cursor_getcursor", "relation": "contains", "confidence": "EXTRACTED", "source_file": "D:\\prism\\apps\\widget\\src\\cursor.ts", "source_location": "L17", "weight": 1.0}, {"source": "d_prism_apps_widget_src_cursor_ts", "target": "cursor_createcursor", "relation": "contains", "confidence": "EXTRACTED", "source_file": "D:\\prism\\apps\\widget\\src\\cursor.ts", "source_location": "L21", "weight": 1.0}, {"source": "d_prism_apps_widget_src_cursor_ts", "target": "cursor_removecursor", "relation": "contains", "confidence": "EXTRACTED", "source_file": "D:\\prism\\apps\\widget\\src\\cursor.ts", "source_location": "L41", "weight": 1.0}, {"source": "d_prism_apps_widget_src_cursor_ts", "target": "cursor_movecursortoelement", "relation": "contains", "confidence": "EXTRACTED", "source_file": "D:\\prism\\apps\\widget\\src\\cursor.ts", "source_location": "L46", "weight": 1.0}, {"source": "d_prism_apps_widget_src_cursor_ts", "target": "cursor_pulsefield", "relation": "contains", "confidence": "EXTRACTED", "source_file": "D:\\prism\\apps\\widget\\src\\cursor.ts", "source_location": "L61", "weight": 1.0}, {"source": "d_prism_apps_widget_src_cursor_ts", "target": "cursor_typeintofield", "relation": "contains", "confidence": "EXTRACTED", "source_file": "D:\\prism\\apps\\widget\\src\\cursor.ts", "source_location": "L73", "weight": 1.0}, {"source": "d_prism_apps_widget_src_cursor_ts", "target": "cursor_animatedfillfields", "relation": "contains", "confidence": "EXTRACTED", "source_file": "D:\\prism\\apps\\widget\\src\\cursor.ts", "source_location": "L120", "weight": 1.0}, {"source": "cursor_removecursor", "target": "cursor_getcursor", "relation": "calls", "confidence": "EXTRACTED", "source_file": "D:\\prism\\apps\\widget\\src\\cursor.ts", "source_location": "L42", "weight": 1.0}, {"source": "cursor_animatedfillfields", "target": "cursor_getcursor", "relation": "calls", "confidence": "EXTRACTED", "source_file": "D:\\prism\\apps\\widget\\src\\cursor.ts", "source_location": "L125", "weight": 1.0}, {"source": "cursor_animatedfillfields", "target": "cursor_createcursor", "relation": "calls", "confidence": "EXTRACTED", "source_file": "D:\\prism\\apps\\widget\\src\\cursor.ts", "source_location": "L126", "weight": 1.0}, {"source": "cursor_animatedfillfields", "target": "cursor_movecursortoelement", "relation": "calls", "confidence": "EXTRACTED", "source_file": "D:\\prism\\apps\\widget\\src\\cursor.ts", "source_location": "L135", "weight": 1.0}, {"source": "cursor_animatedfillfields", "target": "cursor_pulsefield", "relation": "calls", "confidence": "EXTRACTED", "source_file": "D:\\prism\\apps\\widget\\src\\cursor.ts", "source_location": "L136", "weight": 1.0}, {"source": "cursor_animatedfillfields", "target": "cursor_typeintofield", "relation": "calls", "confidence": "EXTRACTED", "source_file": "D:\\prism\\apps\\widget\\src\\cursor.ts", "source_location": "L137", "weight": 1.0}], "raw_calls": [{"caller_nid": "cursor_getcursor", "callee": "getElementById", "source_file": "D:\\prism\\apps\\widget\\src\\cursor.ts", "source_location": "L18"}, {"caller_nid": "cursor_createcursor", "callee": "createElement", "source_file": "D:\\prism\\apps\\widget\\src\\cursor.ts", "source_location": "L22"}, {"caller_nid": "cursor_createcursor", "callee": "assign", "source_file": "D:\\prism\\apps\\widget\\src\\cursor.ts", "source_location": "L25"}, {"caller_nid": "cursor_createcursor", "callee": "appendChild", "source_file": "D:\\prism\\apps\\widget\\src\\cursor.ts", "source_location": "L37"}, {"caller_nid": "cursor_removecursor", "callee": "remove", "source_file": "D:\\prism\\apps\\widget\\src\\cursor.ts", "source_location": "L42"}, {"caller_nid": "cursor_pulsefield", "callee": "setTimeout", "source_file": "D:\\prism\\apps\\widget\\src\\cursor.ts", "source_location": "L66"}, {"caller_nid": "cursor_animatedfillfields", "callee": "entries", "source_file": "D:\\prism\\apps\\widget\\src\\cursor.ts", "source_location": "L131"}, {"caller_nid": "cursor_animatedfillfields", "callee": "getEl", "source_file": "D:\\prism\\apps\\widget\\src\\cursor.ts", "source_location": "L132"}, {"caller_nid": "cursor_animatedfillfields", "callee": "setTimeout", "source_file": "D:\\prism\\apps\\widget\\src\\cursor.ts", "source_location": "L146"}]}